poetry_cdk_plugin/__init__.py
poetry_cdk_plugin/command.py
poetry_cdk_plugin/plugin.py
poetry_cdk_plugin-0.1.6.dist-info/LICENSE
poetry_cdk_plugin-0.1.6.dist-info/METADATA
poetry_cdk_plugin-0.1.6.dist-info/WHEEL
poetry_cdk_plugin-0.1.6.dist-info/entry_points.txt
poetry_cdk_plugin-0.1.6.dist-info/RECORD
