Metadata-Version: 2.1
Name: poetry-cdk-plugin
Version: 0.1.6
Summary: CDK commands for Poetry
Home-page: https://github.com/olivier-schmitt/poetry-cdk-plugin
License: GNU GPL v3
Keywords: CDK,poetry
Author: Olivier Schmitt
Author-email: ursusossforever@gmail.com
Requires-Python: >=3.9,<4.0
Classifier: License :: Other/Proprietary License
Classifier: Programming Language :: Python :: 3
Classifier: Programming Language :: Python :: 3.9
Classifier: Programming Language :: Python :: 3.10
Classifier: Programming Language :: Python :: 3.11
Requires-Dist: coverage (>=7.2.1,<8.0.0)
Requires-Dist: poetry (>=1.3,<2.0)
Requires-Dist: pytest (>=7.2.2,<8.0.0)
Project-URL: Documentation, https://github.com/olivier-schmitt/poetry-cdk-plugin
Project-URL: Repository, https://github.com/olivier-schmitt/poetry-cdk-plugin
